django_auth_wall/__init__.py
django_auth_wall/middleware.py
django_auth_wall-0.3.0.dist-info/METADATA
django_auth_wall-0.3.0.dist-info/WHEEL
django_auth_wall-0.3.0.dist-info/top_level.txt
django_auth_wall-0.3.0.dist-info/RECORD
