Metadata-Version: 2.1
Name: django-auth-wall
Version: 0.3.0
Summary: Puts your staging site behind a basic auth layer.
Home-page: https://github.com/theskumar/django-auth-wall
Author: Saurabh Kumar
Author-email: thes.kumar@gmail.com
License: UNKNOWN
Keywords: security,django,python,basic authentication
Platform: any
Classifier: Environment :: Web Environment
Classifier: Development Status :: 2 - Pre-Alpha
Classifier: Topic :: Internet :: WWW/HTTP :: Dynamic Content
Classifier: Topic :: Software Development :: Libraries :: Python Modules
Classifier: Programming Language :: Python
Classifier: Programming Language :: Python :: 2
Classifier: Programming Language :: Python :: 2.7
Classifier: Programming Language :: Python :: 3
Classifier: Programming Language :: Python :: 3.4
Classifier: Intended Audience :: System Administrators
